CHANGES.rst
MANIFEST.in
README.rst
distribute_setup.py
setup.py
vic_pyramid/__init__.py
vic_pyramid.egg-info/PKG-INFO
vic_pyramid.egg-info/SOURCES.txt
vic_pyramid.egg-info/dependency_links.txt
vic_pyramid.egg-info/entry_points.txt
vic_pyramid.egg-info/not-zip-safe
vic_pyramid.egg-info/requires.txt
vic_pyramid.egg-info/top_level.txt
vic_pyramid/scaffolds/__init__.py
vic_pyramid/scaffolds/vic_pyramid/CHANGES.rst_tmpl
vic_pyramid/scaffolds/vic_pyramid/MANIFEST.in_tmpl
vic_pyramid/scaffolds/vic_pyramid/README.rst_tmpl
vic_pyramid/scaffolds/vic_pyramid/app_cfg.yaml_tmpl
vic_pyramid/scaffolds/vic_pyramid/development.ini_tmpl
vic_pyramid/scaffolds/vic_pyramid/distribute_setup.py
vic_pyramid/scaffolds/vic_pyramid/production.ini_tmpl
vic_pyramid/scaffolds/vic_pyramid/scss.yaml_tmpl
vic_pyramid/scaffolds/vic_pyramid/setup.cfg_tmpl
vic_pyramid/scaffolds/vic_pyramid/setup.py_tmpl
vic_pyramid/scaffolds/vic_pyramid/+package+/__init__.py_tmpl
vic_pyramid/scaffolds/vic_pyramid/+package+/auth.py
vic_pyramid/scaffolds/vic_pyramid/+package+/flash.py
vic_pyramid/scaffolds/vic_pyramid/+package+/i18n.py_tmpl
vic_pyramid/scaffolds/vic_pyramid/+package+/request.py_tmpl
vic_pyramid/scaffolds/vic_pyramid/+package+/utils.py
vic_pyramid/scaffolds/vic_pyramid/+package+/models/__init__.py
vic_pyramid/scaffolds/vic_pyramid/+package+/models/group.py
vic_pyramid/scaffolds/vic_pyramid/+package+/models/permission.py
vic_pyramid/scaffolds/vic_pyramid/+package+/models/tables.py
vic_pyramid/scaffolds/vic_pyramid/+package+/models/user.py
vic_pyramid/scaffolds/vic_pyramid/+package+/modules/__init__.py
vic_pyramid/scaffolds/vic_pyramid/+package+/modules/account/__init__.py
vic_pyramid/scaffolds/vic_pyramid/+package+/modules/account/forms.py_tmpl
vic_pyramid/scaffolds/vic_pyramid/+package+/modules/account/views.py_tmpl
vic_pyramid/scaffolds/vic_pyramid/+package+/modules/account/templates/login.genshi
vic_pyramid/scaffolds/vic_pyramid/+package+/modules/admin/__init__.py_tmpl
vic_pyramid/scaffolds/vic_pyramid/+package+/modules/admin/forms.py_tmpl
vic_pyramid/scaffolds/vic_pyramid/+package+/modules/admin/views.py_tmpl
vic_pyramid/scaffolds/vic_pyramid/+package+/modules/admin/templates/group_create.genshi
