Metadata-Version: 1.0
Name: vic-pyramid
Version: 0.1.4
Summary: Victor's Pyramid Scaffold
Home-page: https://bitbucket.org/victorlin/vic_pyramid
Author: Victor Lin
Author-email: bornstub@gmail.com
License: UNKNOWN
Platform: UNKNOWN
